[
  {
    "id": "147856820",
    "url": "http://vk.com/id147856820",
    "photos": {
      "312155441": [
        "https://pp.userapi.com/c311521/v311521820/3192/VFoTO7LZFHY.jpg",
        162
      ],
      "312031325": [
        "https://pp.userapi.com/c304310/v304310820/67ea/in3yci8Fq1w.jpg",
        100
      ],
      "395395200": [
        "https://pp.userapi.com/c629511/v629511820/2fd53/fy3W_UOeNEU.jpg",
        97
      ]
    }
  },
  {
    "id": "151734285",
    "url": "http://vk.com/id151734285",
    "photos": {
      "431232184": [
        "https://pp.userapi.com/c631426/v631426285/45248/HOu7Qf9rDLk.jpg",
        212
      ],
      "456241119": [
        "https://pp.userapi.com/c639229/v639229412/518be/xknlYLquhA0.jpg",
        117
      ],
      "456240600": [
        "https://pp.userapi.com/c836138/v836138285/4ab5a/OvKcykZfs-g.jpg",
        111
      ]
    }
  },
  {
    "id": "29101075",
    "url": "http://vk.com/id29101075",
    "photos": {
      "438781889": [
        "https://sun9-34.userapi.com/c638120/v638120075/5b0d/EgVw_T6rYoM.jpg",
        52
      ],
      "274806356": [
        "https://pp.userapi.com/c10764/u29101075/-6/w_0999b4ad.jpg",
        44
      ],
      "456239467": [
        "https://pp.userapi.com/c638329/v638329075/57ac1/X9lRtnjGAqg.jpg",
        37
      ]
    }
  },
  {
    "id": "11420084",
    "url": "http://vk.com/id11420084",
    "photos": {
      "383765287": [
        "https://pp.userapi.com/c625631/v625631084/4f612/4Wcb8x5vbaU.jpg",
        287
      ],
      "352001236": [
        "https://pp.userapi.com/c624828/v624828084/1a341/3WFCid4k620.jpg",
        279
      ],
      "295445384": [
        "https://pp.userapi.com/pJZKrT3k2wzpMrKGz6xcq9ipwh3zJ2JnM82gCA/sqPEcUCaMWU.jpg",
        212
      ]
    }
  },
  {
    "id": "196699372",
    "url": "http://vk.com/id196699372",
    "photos": {}
  },
  {
    "id": "249661265",
    "url": "http://vk.com/id249661265",
    "photos": {
      "456240109": [
        "https://pp.userapi.com/c841034/v841034577/58ef9/85PqA16mBR4.jpg",
        78
      ],
      "456239535": [
        "https://pp.userapi.com/c639519/v639519265/1ca5a/Oy0uX-EjdTo.jpg",
        72
      ],
      "456239251": [
        "https://pp.userapi.com/c636716/v636716265/50b3e/2ZfvBLEZX0I.jpg",
        54
      ]
    }
  },
  {
    "id": "198585625",
    "url": "http://vk.com/id198585625",
    "photos": {
      "375951056": [
        "https://pp.userapi.com/c625528/v625528625/3f2bf/-qvmWji9_sw.jpg",
        53
      ],
      "376118231": [
        "https://sun9-9.userapi.com/c623628/v623628625/3f5fe/-niIUW2sWk0.jpg",
        48
      ],
      "375190461": [
        "https://pp.userapi.com/c625528/v625528625/3e11c/83jIc_qxHlU.jpg",
        46
      ]
    }
  },
  {
    "id": "181054359",
    "url": "http://vk.com/id181054359",
    "photos": {
      "327848967": [
        "https://pp.userapi.com/PR_N1WRFJ4zTzCClGA2i0JE5ONqA4YwZdDng4A/jaqI18ftHGM.jpg",
        71
      ],
      "364265744": [
        "https://pp.userapi.com/c622330/v622330359/337e0/G0h-anykg18.jpg",
        69
      ],
      "422056640": [
        "https://sun9-34.userapi.com/c629112/v629112359/24fc3/7v_uGpgcu3g.jpg",
        62
      ]
    }
  },
  {
    "id": "165091321",
    "url": "http://vk.com/id165091321",
    "photos": {
      "380665134": [
        "https://pp.userapi.com/c622027/v622027321/4a99b/m1uPTXZNfSM.jpg",
        273
      ],
      "456245575": [
        "https://pp.userapi.com/c851332/v851332348/bb3b2/auaHY4o1bPY.jpg",
        87
      ],
      "456246466": [
        "https://pp.userapi.com/c851028/v851028897/12f8a9/wVA5OD5t-5s.jpg",
        30
      ]
    }
  },
  {
    "id": "143593300",
    "url": "http://vk.com/id143593300",
    "photos": {
      "433625224": [
        "https://sun9-31.userapi.com/c604522/v604522300/2d535/DV_d0AcFmms.jpg",
        103
      ],
      "420074602": [
        "https://pp.userapi.com/c630322/v630322300/3e718/DdjrirqJGoE.jpg",
        100
      ],
      "440817715": [
        "https://pp.userapi.com/c636317/v636317300/313ca/IJLnnESlq_o.jpg",
        84
      ]
    }
  }
]